Workbook

Sheet Instructions
A1: AFS Compiler — Input Template
A2: Companion workbook for the IFRS for SME's Annual Financial Statements Compiler application
B4: HOW TO USE THIS WORKBOOK
B5: 1. Make one COPY of this workbook per entity, per financial year (e.g. 'PauloJorgePhotography_FY2026.xlsx'). The app reads one workbook = one entity's one financial year, plus its comparative (prior year) column.
B6: 2. Fill in every sheet with the YELLOW cells. Blue text = a cell you type into. Black text = a formula — do not overtype it.
B7: 3. Start with 'Entity Setup' and 'Directors', then 'Trial Balance', 'PPE Register' and 'Loans to-from Shareholders', then 'Tax Computation', then 'Policy Elections'. Finish by checking 'Validation Summary' — every check should read TRUE / 0.
B8: 4. Import this workbook into the app (Entities → Import Workbook), or point the app at the file path if running locally.
B9: 5. Roll forward to next year: in the app, choose 'Create Next Year' for an entity — it exports a new workbook with this year's closing balances pre-filled as next year's opening balances / prior-year comparatives.
B11: WORKED EXAMPLE INCLUDED
B12: Every sheet is pre-populated with a worked example based on Paulo Jorge Photography (Pty) Ltd's FY2026 Annual Financial Statements (year ended 28 February 2026) — the sample AFS the app is being built to reproduce. A handful of immaterial (R1-R2) rounding differences in the original filing have been smoothed out so every total reconciles exactly, which makes this a clean acceptance test: load this workbook into the finished app and the generated AFS should match the structure, wording and (bar those smoothed roundings) the figures of the attached sample.
B13: Delete the example rows / overtype them before compiling a real entity's AFS — do not leave illustrative data in a workbook you intend to compile from.
B15: SHEET GUIDE
B16: • Entity Setup — company registration details, addresses, practitioner, reporting basis, dates.
B17: • Directors — one row per director; used for the Director's Report and signature block.
... B26: The Small Business Corporation (SBC) tax bracket table on the 'Tax Computation' sheet must be updated for each year of assessment — SARS revises the brackets annually. The worked example uses the brackets applicable to financial years ending 1 April 2025 – 31 March 2026 (matching the sample entity's Feb-2026 year end). A second, more recent bracket table (financial years ending 1 April 2026 – 31 March 2027) is shown alongside it for reference — see the comment on that table for the source.

Sheet Entity Setup
A1: Entity Setup
A2: One workbook = one entity, one financial year. Yellow = fill in.
B4: COMPANY DETAILS
B5: Company Name | C5: Example Photography Studio (Pty) Ltd
B6: Registration Number | C6: 2020/000000/07
B7: Tax Reference Number | C7: 0000000000
B8: VAT Number (if registered)
B9: Country of Incorporation and Domicile | C9: South Africa
B10: Nature of Business and Principal Activities | C10: Photography
B11: Registered Office Address | C11: 1 Example Street, Sample City, 0000
B12: Business Address | C12: 1 Example Street, Sample City, 0000
B13: Postal Address | C13: 1 Example Street, Sample City, 0000
B14: Bankers | C14: Example Bank
B16: PRACTITIONER / COMPILER
B17: Practitioner Name | C17: A. Practitioner
B18: Practitioner Firm | C18: Example Accounting Services CC
B19: Report Type | C19: Compilation Report
B21: REPORTING BASIS
B22: Financial Year End (current year) | C22: 46081
B23: Financial Year End (prior/comparative year) | C23: 45716
B24: Date Annual Financial Statements Approved | C24: 46295
B25: IFRS for SME's Edition Applied | C25: Second Edition (2015)
B26: Company Qualifies as a Small Business Corporation (SBC) for tax | C26: Yes
B28: OPENING BALANCES (start of the COMPARATIVE/prior year - needed for the 3-row Statement of Changes in Equity)
B29: Retained Income - Opening Balance (start of prior year) | C29: 138178
B30: Share Capital - Opening Balance (start of prior year) | C30: 1000
B31: Cash and Cash Equivalents - Opening Balance (start of prior year) | C31: 489
B33: PRIOR YEAR SUPPLEMENTARY FIGURE (validation only)
B34: Prior Year Depreciation Charge (total, all asset classes) | C34: 2079

Sheet Directors
A1: Directors
A2: One row per director. Used for the Director's Report and the approval/signature block.
B4: Full Name | C4: Nationality | D4: Date Appointed | E4: Date Resigned (if any) | F4: Signs Approval? (Y/N) | G4: Notes
B5: J. Sample | C5: South African | D5: 41431 | F5: Y

Sheet Trial Balance
A1: Trial Balance
A2: Revenue, cost of sales, operating expenses, investment revenue/finance costs, cash, share capital, receivables/payables. Depreciation is NOT entered here (see PPE Register).
B4: Account Name | C4: AFS Category | D4: Current Year Amount | E4: Prior Year Amount | F4: Notes
B5: Rendering of services | C5: Revenue | D5: 96423 | E5: 41899
B6: Purchases | C6: Cost of Sales | D6: 8122 | E6: 12892
B7: Accounting fees | C7: Operating Expense | D7: 13628 | E7: 5750
B8: Advertising | C8: Operating Expense | D8: 5251 | E8: 0
B9: Bank charges | C9: Operating Expense | D9: 5803 | E9: 3941
B10: Consumables | C10: Operating Expense | D10: 1495 | E10: 0
B11: Employee costs | C11: Operating Expense | D11: 10300 | E11: 0
B12: Entertainment | C12: Operating Expense | D12: 2815 | E12: 144
B13: IT expenses | C13: Operating Expense | D13: 5266 | E13: 4482
B14: Levies | C14: Operating Expense | D14: 2600 | E14: 2050
B15: Motor vehicle expenses | C15: Operating Expense | D15: 9169 | E15: 3812
B16: Petrol and oil | C16: Operating Expense | D16: 11192 | E16: 6712
... B23: Cash and cash equivalents | C23: Cash and Cash Equivalents | D23: 6178 | E23: 430
B24: Share capital | C24: Share Capital | D24: 1000 | E24: 1000 | F24: Ordinary shares, unchanged during both years
B34: CATEGORY SUBTOTALS (formulas - do not edit)
B35: AFS Category | C35: Current Year | D35: Prior Year
B36: Revenue | C36: =SUMIF($C$5:$C$32,$B36,$D$5:$D$32) | D36: =SUMIF($C$5:$C$32,$B36,$E$5:$E$32)
B37: Cost of Sales | C37: =SUMIF($C$5:$C$32,$B37,$D$5:$D$32) | D37: =SUMIF($C$5:$C$32,$B37,$E$5:$E$32)
B38: Operating Expense | C38: =SUMIF($C$5:$C$32,$B38,$D$5:$D$32) | D38: =SUMIF($C$5:$C$32,$B38,$E$5:$E$32)
B39: Investment Revenue | C39: =SUMIF($C$5:$C$32,$B39,$D$5:$D$32) | D39: =SUMIF($C$5:$C$32,$B39,$E$5:$E$32)
B40: Finance Costs | C40: =SUMIF($C$5:$C$32,$B40,$D$5:$D$32) | D40: =SUMIF($C$5:$C$32,$B40,$E$5:$E$32)
B41: Other Income | C41: =SUMIF($C$5:$C$32,$B41,$D$5:$D$32) | D41: =SUMIF($C$5:$C$32,$B41,$E$5:$E$32)
B42: Trade and Other Receivables | C42: =SUMIF($C$5:$C$32,$B42,$D$5:$D$32) | D42: =SUMIF($C$5:$C$32,$B42,$E$5:$E$32)
B43: Inventory | C43: =SUMIF($C$5:$C$32,$B43,$D$5:$D$32) | D43: =SUMIF($C$5:$C$32,$B43,$E$5:$E$32)
B44: Cash and Cash Equivalents | C44: =SUMIF($C$5:$C$32,$B44,$D$5:$D$32) | D44: =SUMIF($C$5:$C$32,$B44,$E$5:$E$32)
B45: Share Capital | C45: =SUMIF($C$5:$C$32,$B45,$D$5:$D$32) | D45: =SUMIF($C$5:$C$32,$B45,$E$5:$E$32)
B46: Trade and Other Payables | C46: =SUMIF($C$5:$C$32,$B46,$D$5:$D$32) | D46: =SUMIF($C$5:$C$32,$B46,$E$5:$E$32)
B47: Current Tax Payable | C47: =SUMIF($C$5:$C$32,$B47,$D$5:$D$32) | D47: =SUMIF($C$5:$C$32,$B47,$E$5:$E$32)
... B50: Other Non-Current Liability | C50: =SUMIF($C$5:$C$32,$B50,$D$5:$D$32) | D50: =SUMIF($C$5:$C$32,$B50,$E$5:$E$32)

Sheet PPE Register
A1: PPE Register
A2: One row per asset class. Drives the Property, Plant and Equipment note, the depreciation charge, and the cash flow 'Purchase of PPE' line.
B4: Asset Category | C4: Depreciation Method | D4: Useful Life (yrs) | E4: Opening Cost | F4: Additions | G4: Disposals - Cost | H4: Closing Cost | I4: Opening Accum. Depreciation | J4: Depreciation Charge | K4: Accum. Depreciation on Disposals | L4: Closing Accum. Depreciation | M4: Carrying Value
B5: Office equipment | C5: Straight line | D5: 6 | E5: 7200 | F5: 0 | G5: 0 | H5: =E5+F5-G5 | I5: 7199 | J5: 0 | K5: 0 | L5: =I5+J5-K5 | M5: =H5-L5
B6: IT equipment | C6: Straight line | D6: 3 | E6: 6300 | F6: 0 | G6: 0 | H6: =E6+F6-G6 | I6: 5891 | J6: 408 | K6: 0 | L6: =I6+J6-K6 | M6: =H6-L6
H7: =E7+F7-G7 | L7: =I7+J7-K7 | M7: =H7-L7
H8: =E8+F8-G8 | L8: =I8+J8-K8 | M8: =H8-L8
H9: =E9+F9-G9 | L9: =I9+J9-K9 | M9: =H9-L9
H10: =E10+F10-G10 | L10: =I10+J10-K10 | M10: =H10-L10
B11: Total | E11: =SUM(E5:E10) | F11: =SUM(F5:F10) | G11: =SUM(G5:G10) | H11: =SUM(H5:H10) | I11: =SUM(I5:I10) | J11: =SUM(J5:J10) | K11: =SUM(K5:K10) | L11: =SUM(L5:L10) | M11: =SUM(M5:M10)

Sheet Loans to-from Shareholders
A1: Loans to-from Shareholders
A2: One row per director/shareholder loan account. Drives the loan note and the related cash flow movement.
B4: Shareholder / Director Name | C4: Direction (To / From) | D4: Opening Balance | E4: Advances | F4: Repayments | G4: Interest Rate % p.a. | H4: Interest Charged (received in cash) | I4: Closing Balance | J4: Secured / Unsecured | K4: Repayment Terms
B5: J. Sample | C5: To | D5: 146518 | E5: 18107 | F5: 0 | G5: 0.0775 | H5: 11841 | I5: =D5+E5-F5 | J5: Unsecured | K5: No fixed terms of repayment have been set
I6: =D6+E6-F6
I7: =D7+E7-F7
I8: =D8+E8-F8
I9: =D9+E9-F9
B10: Total | D10: =SUM(D5:D9) | E10: =SUM(E5:E9) | F10: =SUM(F5:F9) | H10: =SUM(H5:H9) | I10: =SUM(I5:I9)

Sheet Tax Computation
A1: Tax Computation
A2: Current-tax computation for the year, plus the editable SBC / company tax bracket table the app uses to calculate the tax charge.
B4: Net profit per income statement | C4: ='Trial Balance'!C36-'Trial Balance'!C37-'Trial Balance'!C38-'PPE Register'!J11+'Trial Balance'!C39-'Trial Balance'!C40
B6: Temporary differences
B7: Description | C7: Amount
B8: Plant and machinery where company qualifies as SBC: s12E wear-and-tear | C8: =-'PPE Register'!J11
B9: Depreciation according to the financial statements | C9: ='PPE Register'!J11
B12: Total temporary differences | C12: =SUM(C8:C11)
B14: Calculated tax profit for the year | C14: =C4+C12
B15: Assessed loss brought forward | C15: 0
B16: Assessed loss utilised | C16: =-MIN(C15,MAX(0,C14))
B17: Taxable income for the year | C17: =MAX(0,C14+C16)
B18: Assessed loss carried forward | C18: =MAX(0,C15+C16)+MAX(0,-(C14+C16))
B20: SBC / Company tax bracket table - EDIT FOR THE APPLICABLE YEAR OF ASSESSMENT
B21: Lower Limit | C21: Upper Limit | D21: Rate
B22: 0 | C22: 95750 | D22: 0
B23: 95751 | C23: 365000 | D23: 0.07
B24: 365001 | C24: 550000 | D24: 0.21
B25: 550001 | C25: N/A | D25: 0.27
B27: Reference only - SBC brackets for financial years ending 1 April 2026 - 31 March 2027
B28: 1 | C28: 99000 | D28: 0
B29: 99001 | C29: 365000 | D29: 0.07
B30: 365001 | C30: 550000 | D30: 0.21
B31: 550001 | C31: N/A | D31: 0.27
B33: Tax thereon @ rate determined in the table above
C34: =(MAX(0,MIN(C$17,C22)-(B22-1)))*D22+(MAX(0,MIN(C$17,C23)-(B23-1)))*D23+(MAX(0,MIN(C$17,C24)-(B24-1)))*D24+(MAX(0,C$17-(B25-1)))*D25

Sheet Policy Elections
A1: Policy Elections
A2: Tick which IFRS for SME's accounting policy sections apply, so the app only prints the policies (and matching notes) relevant to this entity.
B4: Accounting Policy Area (IFRS for SME's Section) | C4: Applicable? (Y/N) | D4: Notes
B5: Property, plant and equipment (Section 17) | C5: Y | D5: Straight-line depreciation per the PPE Register
B6: Financial instruments (Sections 11 & 12) | C6: Y | D6: Loans, cash, trade receivables/payables at amortised cost
B7: Income tax, current and deferred (Section 29) | C7: Y
B8: Employee benefits, short-term (Section 28) | C8: Y
B9: Revenue (Section 23) | C9: Y | D9: Rendering of services - stage of completion
B10: Inventories (Section 13) | C10: N | D10: Set to Y if the entity holds inventory
B11: Leases (Section 20) | C11: N
B12: Provisions and contingencies (Section 21) | C12: N
B13: Related party disclosures (Section 33) | C13: Y | D13: Director/shareholder loan account
B14: Impairment of assets (Section 27) | C14: N
B15: Foreign currency translation (Section 30) | C15: N
B16: Government grants (Section 24) | C16: N
B17: Borrowing costs (Section 25) | C17: N
B18: Statement of cash flows (Section 7) | C18: Y | D18: Indirect/direct method as applicable

Sheet Validation Summary
A1: Validation Summary
A2: Read-only cross-checks. Every 'Difference' cell must read 0 before you import this workbook into the app.
B4: Check | C4: Total Assets | D4: Total Equity + Liabilities | E4: Difference
B5: Total Assets = Total Equity + Liabilities (current year) | C5: ='PPE Register'!M11+'Loans to-from Shareholders'!I10+'Trial Balance'!C44+'Trial Balance'!C42+'Trial Balance'!C43+'Trial Balance'!C48 | D5: ='Trial Balance'!C45+('Entity Setup'!C29+('Trial Balance'!D36-'Trial Balance'!D37-'Trial Balance'!D38-'Entity Setup'!C34+'Trial Balance'!D39-'Trial Balance'!D40)+'Tax Computation'!C4)+'Trial Balance'!C46+'Trial Balance'!C47+'Trial Balance'!C49+'Trial Balance'!C50 | E5: =C5-D5
B7: Check | C7: Computed A | D7: Computed B | E7: Difference
B8: Cash Flow computed closing cash vs Statement of Financial Position cash | C8: ='Trial Balance'!D44+('Trial Balance'!C36-('Trial Balance'!C37+'Trial Balance'!C38)+'Trial Balance'!C39-'Trial Balance'!C40)+(-'PPE Register'!F11+('Loans to-from Shareholders'!F10-'Loans to-from Shareholders'!E10)) | D8: ='Trial Balance'!C44 | E8: =C8-D8
B9: PPE Register total carrying value vs its own cost-less-depreciation total | C9: ='PPE Register'!M11 | D9: ='PPE Register'!H11-'PPE Register'!L11 | E9: =C9-D9
B10: Loans Register closing balance vs Opening + Advances - Repayments | C10: ='Loans to-from Shareholders'!I10 | D10: ='Loans to-from Shareholders'!D10+'Loans to-from Shareholders'!E10-'Loans to-from Shareholders'!F10 | E10: =C10-D10
B11: Retained income roll-forward: prior-year closing vs current-year opening | C11: ='Entity Setup'!C29+('Trial Balance'!D36-'Trial Balance'!D37-'Trial Balance'!D38-'Entity Setup'!C34+'Trial Balance'!D39-'Trial Balance'!D40) | D11: ='Entity Setup'!C29+('Trial Balance'!D36-'Trial Balance'!D37-'Trial Balance'!D38-'Entity Setup'!C34+'Trial Balance'!D39-'Trial Balance'!D40) | E11: =C11-D11
B13: All 'Difference' columns above must equal 0 (formatted as '-'). A non-zero difference means an input sheet is inconsistent - fix it before importing.
